{
  "project_info": {
    "project_number": "1024441459942",
    "project_id": "medex-b36ec",
    "storage_bucket": "medex-b36ec.firebasestorage.app"
  },
  "client": [
    {
      "client_info": {
        "mobilesdk_app_id": "1:1024441459942:android:654c390014a77a2a094727",
        "android_client_info": {
          "package_name": "com.josea.laboratorio_3"
        }
      },
      "oauth_client": [],
      "api_key": [
        {
          "current_key": "AIzaSyAg7SRPTGUcDSKBdRaNs-Ba8Jmybm_LjU0"
        }
      ],
      "services": {
        "appinvite_service": {
          "other_platform_oauth_client": []
        }
      }
    }
  ],
  "configuration_version": "1"
}